azureml/__init__.py
azureml/contrib/__init__.py
azureml/contrib/_mircli/__init__.py
azureml/contrib/_mircli/_cli.py
azureml/contrib/_mircli/_util.py
azureml/contrib/mir/__init__.py
azureml/contrib/mir/webservice/__init__.py
azureml/contrib/mir/webservice/_util.py
azureml/contrib/mir/webservice/mir.py
azureml/contrib/mir/webservice/data/mir_service_payload_template.json
azureml_contrib_mir-1.60.0.dist-info/licenses/LICENSE.txt
azureml_contrib_mir-1.60.0.dist-info/METADATA
azureml_contrib_mir-1.60.0.dist-info/WHEEL
azureml_contrib_mir-1.60.0.dist-info/top_level.txt
azureml_contrib_mir-1.60.0.dist-info/RECORD
